{
  "solves": [
    {
      "category": "Crypto", 
      "chal": "Bad Restaurant", 
      "chalid": 8, 
      "team": 339, 
      "time": 1512242436, 
      "value": 5
    }, 
    {
      "category": "Award", 
      "chal": "Hint for Bad Restaurant", 
      "chalid": null, 
      "team": 339, 
      "time": 1512242577, 
      "value": 0
    }, 
    {
      "category": "Slightly More Trivial", 
      "chal": "Sanity Check", 
      "chalid": 12, 
      "team": 339, 
      "time": 1512242701, 
      "value": 1
    }, 
    {
      "category": "Award", 
      "chal": "Hint for Zalgo", 
      "chalid": null, 
      "team": 339, 
      "time": 1512243017, 
      "value": 0
    }, 
    {
      "category": "Slightly More Trivial", 
      "chal": "trivial rev", 
      "chalid": 34, 
      "team": 339, 
      "time": 1512243344, 
      "value": 2
    }, 
    {
      "category": "Slightly More Trivial", 
      "chal": "trivial stego", 
      "chalid": 33, 
      "team": 339, 
      "time": 1512245993, 
      "value": 3
    }, 
    {
      "category": "Award", 
      "chal": "Hint for trivial arithmetic", 
      "chalid": null, 
      "team": 339, 
      "time": 1512256558, 
      "value": 0
    }, 
    {
      "category": "Award", 
      "chal": "Hint for Secret Doc", 
      "chalid": null, 
      "team": 339, 
      "time": 1512258144, 
      "value": 0
    }, 
    {
      "category": "Award", 
      "chal": "Hint for Secret Doc", 
      "chalid": null, 
      "team": 339, 
      "time": 1512258193, 
      "value": 0
    }, 
    {
      "category": "Award", 
      "chal": "Hint for Ads", 
      "chalid": null, 
      "team": 339, 
      "time": 1512258993, 
      "value": 0
    }, 
    {
      "category": "Award", 
      "chal": "Hint for What is this place?", 
      "chalid": null, 
      "team": 339, 
      "time": 1512259435, 
      "value": 0
    }, 
    {
      "category": "Award", 
      "chal": "Hint for Public key? What about <i>no</i> key?", 
      "chalid": null, 
      "team": 339, 
      "time": 1512259923, 
      "value": 0
    }, 
    {
      "category": "Award", 
      "chal": "Hint for You are nothing", 
      "chalid": null, 
      "team": 339, 
      "time": 1512263574, 
      "value": 0
    }
  ]
}
