{
  "solves": [
    {
      "category": "Crypto", 
      "chal": "Bad Restaurant", 
      "chalid": 8, 
      "team": 561, 
      "time": 1512254178, 
      "value": 5
    }, 
    {
      "category": "Slightly More Trivial", 
      "chal": "Sanity Check", 
      "chalid": 12, 
      "team": 561, 
      "time": 1512271377, 
      "value": 1
    }, 
    {
      "category": "Award", 
      "chal": "Hint for Zalgo", 
      "chalid": null, 
      "team": 561, 
      "time": 1512271390, 
      "value": 0
    }, 
    {
      "category": "Award", 
      "chal": "Hint for Secret Doc", 
      "chalid": null, 
      "team": 561, 
      "time": 1512271573, 
      "value": 0
    }, 
    {
      "category": "Award", 
      "chal": "Hint for Secret Doc", 
      "chalid": null, 
      "team": 561, 
      "time": 1512271584, 
      "value": 0
    }, 
    {
      "category": "Award", 
      "chal": "Hint for You are nothing", 
      "chalid": null, 
      "team": 561, 
      "time": 1512272306, 
      "value": 0
    }, 
    {
      "category": "Award", 
      "chal": "Hint for Not Quite LSD", 
      "chalid": null, 
      "team": 561, 
      "time": 1512272573, 
      "value": 0
    }, 
    {
      "category": "Web", 
      "chal": "Ads", 
      "chalid": 24, 
      "team": 561, 
      "time": 1512272739, 
      "value": 20
    }, 
    {
      "category": "Award", 
      "chal": "Hint for 768", 
      "chalid": null, 
      "team": 561, 
      "time": 1512272857, 
      "value": 0
    }, 
    {
      "category": "Slightly More Trivial", 
      "chal": "Zalgo", 
      "chalid": 13, 
      "team": 561, 
      "time": 1512273533, 
      "value": 2
    }, 
    {
      "category": "Award", 
      "chal": "Hint for IRC", 
      "chalid": null, 
      "team": 561, 
      "time": 1512356436, 
      "value": 0
    }
  ]
}
