{
  "solves": [
    {
      "category": "Award", 
      "chal": "Hint for Ads", 
      "chalid": null, 
      "team": 697, 
      "time": 1512314292, 
      "value": 0
    }, 
    {
      "category": "Slightly More Trivial", 
      "chal": "Sanity Check", 
      "chalid": 12, 
      "team": 697, 
      "time": 1512314396, 
      "value": 1
    }, 
    {
      "category": "Slightly More Trivial", 
      "chal": "trivial rev", 
      "chalid": 34, 
      "team": 697, 
      "time": 1512314447, 
      "value": 2
    }
  ]
}
