{
  "solves": [
    {
      "category": "Award", 
      "chal": "Hint for Bad Restaurant", 
      "chalid": null, 
      "team": 720, 
      "time": 1512326738, 
      "value": 0
    }, 
    {
      "category": "Slightly More Trivial", 
      "chal": "Sanity Check", 
      "chalid": 12, 
      "team": 720, 
      "time": 1512326767, 
      "value": 1
    }, 
    {
      "category": "Award", 
      "chal": "Hint for Zalgo", 
      "chalid": null, 
      "team": 720, 
      "time": 1512326775, 
      "value": 0
    }, 
    {
      "category": "Slightly More Trivial", 
      "chal": "Zalgo", 
      "chalid": 13, 
      "team": 720, 
      "time": 1512326798, 
      "value": 2
    }, 
    {
      "category": "Award", 
      "chal": "Hint for trivial arithmetic", 
      "chalid": null, 
      "team": 720, 
      "time": 1512326842, 
      "value": 0
    }, 
    {
      "category": "Award", 
      "chal": "Hint for Ads", 
      "chalid": null, 
      "team": 720, 
      "time": 1512326870, 
      "value": 0
    }, 
    {
      "category": "Award", 
      "chal": "Hint for What is this place?", 
      "chalid": null, 
      "team": 720, 
      "time": 1512327082, 
      "value": 0
    }, 
    {
      "category": "Award", 
      "chal": "Hint for Management", 
      "chalid": null, 
      "team": 720, 
      "time": 1512327112, 
      "value": 0
    }, 
    {
      "category": "Web", 
      "chal": "IRC", 
      "chalid": 23, 
      "team": 720, 
      "time": 1512327265, 
      "value": 50
    }, 
    {
      "category": "Award", 
      "chal": "Hint for Secret Doc", 
      "chalid": null, 
      "team": 720, 
      "time": 1512327447, 
      "value": 0
    }, 
    {
      "category": "Award", 
      "chal": "Hint for Secret Doc", 
      "chalid": null, 
      "team": 720, 
      "time": 1512327450, 
      "value": 0
    }, 
    {
      "category": "Award", 
      "chal": "Hint for Rick", 
      "chalid": null, 
      "team": 720, 
      "time": 1512327678, 
      "value": 0
    }, 
    {
      "category": "Award", 
      "chal": "Hint for Sorta", 
      "chalid": null, 
      "team": 720, 
      "time": 1512327719, 
      "value": 0
    }, 
    {
      "category": "Award", 
      "chal": "Hint for Word Find", 
      "chalid": null, 
      "team": 720, 
      "time": 1512327732, 
      "value": 0
    }, 
    {
      "category": "Crypto", 
      "chal": "Bad Restaurant", 
      "chalid": 8, 
      "team": 720, 
      "time": 1512328136, 
      "value": 5
    }, 
    {
      "category": "Award", 
      "chal": "Hint for 768", 
      "chalid": null, 
      "team": 720, 
      "time": 1512328204, 
      "value": 0
    }, 
    {
      "category": "Award", 
      "chal": "Hint for You are nothing", 
      "chalid": null, 
      "team": 720, 
      "time": 1512328215, 
      "value": 0
    }, 
    {
      "category": "Award", 
      "chal": "Hint for You are nothing", 
      "chalid": null, 
      "team": 720, 
      "time": 1512328220, 
      "value": 0
    }
  ]
}
