{
  "solves": [
    {
      "category": "Slightly More Trivial", 
      "chal": "Sanity Check", 
      "chalid": 12, 
      "team": 76, 
      "time": 1512242137, 
      "value": 1
    }, 
    {
      "category": "Crypto", 
      "chal": "Bad Restaurant", 
      "chalid": 8, 
      "team": 76, 
      "time": 1512242312, 
      "value": 5
    }, 
    {
      "category": "Steganography", 
      "chal": "Not Quite LSD", 
      "chalid": 3, 
      "team": 76, 
      "time": 1512243126, 
      "value": 30
    }, 
    {
      "category": "Award", 
      "chal": "Hint for Zalgo", 
      "chalid": null, 
      "team": 76, 
      "time": 1512244467, 
      "value": 0
    }, 
    {
      "category": "Award", 
      "chal": "Hint for Ads", 
      "chalid": null, 
      "team": 76, 
      "time": 1512244609, 
      "value": 0
    }, 
    {
      "category": "Award", 
      "chal": "Hint for Secret Doc", 
      "chalid": null, 
      "team": 76, 
      "time": 1512244686, 
      "value": 0
    }, 
    {
      "category": "Award", 
      "chal": "Hint for Secret Doc", 
      "chalid": null, 
      "team": 76, 
      "time": 1512244691, 
      "value": 0
    }, 
    {
      "category": "Award", 
      "chal": "Hint for Strange Message", 
      "chalid": null, 
      "team": 76, 
      "time": 1512244782, 
      "value": 0
    }, 
    {
      "category": "Award", 
      "chal": "Hint for Strange Message", 
      "chalid": null, 
      "team": 76, 
      "time": 1512244789, 
      "value": 0
    }, 
    {
      "category": "Award", 
      "chal": "Hint for Woah!", 
      "chalid": null, 
      "team": 76, 
      "time": 1512244805, 
      "value": 0
    }, 
    {
      "category": "Award", 
      "chal": "Hint for Management", 
      "chalid": null, 
      "team": 76, 
      "time": 1512244898, 
      "value": 0
    }, 
    {
      "category": "Slightly More Trivial", 
      "chal": "Zalgo", 
      "chalid": 13, 
      "team": 76, 
      "time": 1512245191, 
      "value": 2
    }, 
    {
      "category": "Award", 
      "chal": "Hint for trivial arithmetic", 
      "chalid": null, 
      "team": 76, 
      "time": 1512245437, 
      "value": 0
    }, 
    {
      "category": "Slightly More Trivial", 
      "chal": "trivial arithmetic", 
      "chalid": 31, 
      "team": 76, 
      "time": 1512245539, 
      "value": 4
    }, 
    {
      "category": "Award", 
      "chal": "Hint for 768", 
      "chalid": null, 
      "team": 76, 
      "time": 1512246321, 
      "value": 0
    }, 
    {
      "category": "Award", 
      "chal": "Hint for Rick", 
      "chalid": null, 
      "team": 76, 
      "time": 1512246349, 
      "value": 0
    }, 
    {
      "category": "Award", 
      "chal": "Hint for You are nothing", 
      "chalid": null, 
      "team": 76, 
      "time": 1512246745, 
      "value": 0
    }, 
    {
      "category": "Award", 
      "chal": "Hint for What is this place?", 
      "chalid": null, 
      "team": 76, 
      "time": 1512258048, 
      "value": 0
    }
  ]
}
