{
  "solves": [
    {
      "category": "Award", 
      "chal": "Hint for Ads", 
      "chalid": null, 
      "team": 86, 
      "time": 1512234453, 
      "value": 0
    }, 
    {
      "category": "Award", 
      "chal": "Hint for Twirl", 
      "chalid": null, 
      "team": 86, 
      "time": 1512234655, 
      "value": 0
    }, 
    {
      "category": "Crypto", 
      "chal": "Bad Restaurant", 
      "chalid": 8, 
      "team": 86, 
      "time": 1512235078, 
      "value": 5
    }, 
    {
      "category": "Crypto", 
      "chal": "768", 
      "chalid": 9, 
      "team": 86, 
      "time": 1512237201, 
      "value": 30
    }, 
    {
      "category": "Award", 
      "chal": "Hint for Zalgo", 
      "chalid": null, 
      "team": 86, 
      "time": 1512243197, 
      "value": 0
    }, 
    {
      "category": "Slightly More Trivial", 
      "chal": "Zalgo", 
      "chalid": 13, 
      "team": 86, 
      "time": 1512243291, 
      "value": 2
    }, 
    {
      "category": "Slightly More Trivial", 
      "chal": "trivial arithmetic", 
      "chalid": 31, 
      "team": 86, 
      "time": 1512243526, 
      "value": 4
    }, 
    {
      "category": "Award", 
      "chal": "Hint for trivial arithmetic", 
      "chalid": null, 
      "team": 86, 
      "time": 1512243528, 
      "value": 0
    }, 
    {
      "category": "Slightly More Trivial", 
      "chal": "trivial rsa", 
      "chalid": 32, 
      "team": 86, 
      "time": 1512244674, 
      "value": 3
    }, 
    {
      "category": "Slightly More Trivial", 
      "chal": "trivial stego", 
      "chalid": 33, 
      "team": 86, 
      "time": 1512245854, 
      "value": 3
    }, 
    {
      "category": "Award", 
      "chal": "Hint for Not Quite LSD", 
      "chalid": null, 
      "team": 86, 
      "time": 1512246705, 
      "value": 0
    }, 
    {
      "category": "Award", 
      "chal": "Hint for Secret Doc", 
      "chalid": null, 
      "team": 86, 
      "time": 1512246818, 
      "value": 0
    }, 
    {
      "category": "Award", 
      "chal": "Hint for Secret Doc", 
      "chalid": null, 
      "team": 86, 
      "time": 1512246822, 
      "value": 0
    }, 
    {
      "category": "Slightly More Trivial", 
      "chal": "Sanity Check", 
      "chalid": 12, 
      "team": 86, 
      "time": 1512247536, 
      "value": 1
    }, 
    {
      "category": "Slightly More Trivial", 
      "chal": "trivial rev", 
      "chalid": 34, 
      "team": 86, 
      "time": 1512247586, 
      "value": 2
    }, 
    {
      "category": "Award", 
      "chal": "Hint for Public key? What about <i>no</i> key?", 
      "chalid": null, 
      "team": 86, 
      "time": 1512247833, 
      "value": 0
    }, 
    {
      "category": "Award", 
      "chal": "Hint for Lost Flag", 
      "chalid": null, 
      "team": 86, 
      "time": 1512248234, 
      "value": 0
    }, 
    {
      "category": "Misc", 
      "chal": "That's not latin...", 
      "chalid": 14, 
      "team": 86, 
      "time": 1512248357, 
      "value": 10
    }, 
    {
      "category": "Award", 
      "chal": "Hint for You are nothing", 
      "chalid": null, 
      "team": 86, 
      "time": 1512289751, 
      "value": 0
    }
  ]
}
